django_latch-0.3.data/data/locales/django.mo
django_latch-0.3.data/data/locales/django.po
django_latch-0.3.data/data/templates/latch_pair.html
django_latch-0.3.data/data/templates/latch_status.html
django_latch-0.3.data/data/templates/latch_unpair.html
latch/__init__.py
latch/admin.py
latch/apps.py
latch/auth_backend.py
latch/forms.py
latch/models.py
latch/signals.py
latch/urls.py
latch/views.py
latch/latch_sdk_python/__init__.py
latch/latch_sdk_python/error.py
latch/latch_sdk_python/latch.py
latch/latch_sdk_python/latchapp.py
latch/latch_sdk_python/latchauth.py
latch/latch_sdk_python/latchresponse.py
latch/latch_sdk_python/latchuser.py
latch/locale/es/LC_MESSAGES/django.mo
latch/locale/es/LC_MESSAGES/django.po
latch/migrations/0001_initial.py
latch/migrations/0002_drop_latch_setup.py
latch/migrations/__init__.py
latch/templates/latch_pair.html
latch/templates/latch_status.html
latch/templates/latch_unpair.html
django_latch-0.3.dist-info/LICENSE
django_latch-0.3.dist-info/METADATA
django_latch-0.3.dist-info/WHEEL
django_latch-0.3.dist-info/top_level.txt
django_latch-0.3.dist-info/RECORD
