Metadata-Version: 2.1
Name: django-latch
Version: 0.3
Summary: Django latch module.
Home-page: https://github.com/javimoral/django-latch
Author: Javier Moral et al. (see README)
Author-email: moraljlara@gmail.com
License: Apache License 2.0
Platform: UNKNOWN
Classifier: Programming Language :: Python
Classifier: License :: OSI Approved :: BSD License
Classifier: Development Status :: 4 - Beta
Classifier: Operating System :: OS Independent
Classifier: Framework :: Django
Classifier: Intended Audience :: Developers
Classifier: Topic :: Internet :: WWW/HTTP :: Dynamic Content
Requires-Dist: Django (>=2.0)
